_py_backend/__init__.py
CoolProp/typedefs.pxd
CoolProp/CoolProp.pxd
CoolProp/State.pxd
CoolProp/cAbstractState.pxd
CoolProp/constants_header.pxd
CoolProp/constants.py
CoolProp/__init__.py
CoolProp/AbstractState.pxd
CoolProp/_constants.cpython-311-darwin.so
CoolProp/BibtexParser.py
CoolProp/HumidAirProp.py
CoolProp/CoolPropBibTeXLibrary.bib
CoolProp/superancillary.pxd
CoolProp/CoolProp.cpython-311-darwin.so
CoolProp/State.py
CoolProp/include/PolyMath.h
CoolProp/include/CoolPropFluid.h
CoolProp/include/Ancillaries.h
CoolProp/include/CPmsgpack.h
CoolProp/include/cpversion.h
CoolProp/include/gitrevision.h
CoolProp/include/PhaseEnvelope.h
CoolProp/include/CPfilepaths.h
CoolProp/include/Tests.h
CoolProp/include/CoolPropTools.h
CoolProp/include/DataStructures.h
CoolProp/include/CoolPropLib.h
CoolProp/include/Exceptions.h
CoolProp/include/PlatformDetermination.h
CoolProp/include/PCSAFTFluid.h
CoolProp/include/Solvers.h
CoolProp/include/Configuration.h
CoolProp/include/Helmholtz.h
CoolProp/include/MatrixMath.h
CoolProp/include/CoolPropPlot.h
CoolProp/include/AbstractState.h
CoolProp/include/CoolProp.h
CoolProp/include/CPstrings.h
CoolProp/include/miniz.h
CoolProp/include/crossplatform_shared_ptr.h
CoolProp/include/CPnumerics.h
CoolProp/include/IdealCurves.h
CoolProp/include/TestObjects.h
CoolProp/include/.gitignore
CoolProp/include/ODEIntegrators.h
CoolProp/include/HumidAirProp.h
CoolProp/include/Ice.h
CoolProp/include/finite_diff.h
CoolProp/include/CachedElement.h
CoolProp/include/rapidjson_include.h
CoolProp/include/SpeedTest.h
CoolProp/include/IncompressibleFluid.h
CoolProp/include/fmt/ostream.h
CoolProp/include/fmt/format-inl.h
CoolProp/include/fmt/ranges.h
CoolProp/include/fmt/xchar.h
CoolProp/include/fmt/core.h
CoolProp/include/fmt/chrono.h
CoolProp/include/fmt/os.h
CoolProp/include/fmt/color.h
CoolProp/include/fmt/args.h
CoolProp/include/fmt/printf.h
CoolProp/include/fmt/compile.h
coolprop-7.1.0.dist-info/RECORD
coolprop-7.1.0.dist-info/WHEEL
coolprop-7.1.0.dist-info/top_level.txt
coolprop-7.1.0.dist-info/METADATA
